meu_pacote/__init__.py
meu_pacote/minha_lib.py
meu_pacote_renanzin_estudo_poetry-0.0.1.dist-info/METADATA
meu_pacote_renanzin_estudo_poetry-0.0.1.dist-info/WHEEL
meu_pacote_renanzin_estudo_poetry-0.0.1.dist-info/entry_points.txt
meu_pacote_renanzin_estudo_poetry-0.0.1.dist-info/top_level.txt
meu_pacote_renanzin_estudo_poetry-0.0.1.dist-info/RECORD
