Metadata-Version: 2.4
Name: meu_pacote-renanzin-estudo-poetry
Version: 0.0.1
Requires-Dist: httpx
Dynamic: requires-dist
